pycli_template/__init__.py
pycli_template/cli.py
pycli_template/test_cli.py
pycli_template-0.0.2.dist-info/METADATA
pycli_template-0.0.2.dist-info/WHEEL
pycli_template-0.0.2.dist-info/entry_points.txt
pycli_template-0.0.2.dist-info/RECORD
