Metadata-Version: 2.4
Name: pycli-template
Version: 0.0.2
Summary: A command-line tool
Project-URL: Homepage, https://example.com
Project-URL: Documentation, https://example.com/docs
Project-URL: Repository, https://github.com/DevOpsJeremy/pycli-template
Project-URL: Issues, https://github.com/DevOpsJeremy/pycli-template/issues
Project-URL: Changelog, https://github.com/DevOpsJeremy/pycli-template/blob/main/CHANGELOG.md
Author-email: Jeremy Watkins <DevOpsJeremy@gmail.com>
Maintainer-email: Jeremy Watkins <DevOpsJeremy@gmail.com>
License-Expression: MIT
Keywords: cli
Classifier: Development Status :: 4 - Beta
Classifier: Programming Language :: Python
Requires-Dist: click
